quintoandar_eb_deployer/__init__.py
quintoandar_eb_deployer/app_settings.py
quintoandar_eb_deployer/management/__init__.py
quintoandar_eb_deployer/management/commands/__init__.py
quintoandar_eb_deployer/management/commands/_awsElasticbeanstalkPush.py
quintoandar_eb_deployer/management/commands/deploy.py
quintoandar_eb_deployer/management/commands/aws/__init__.py
quintoandar_eb_deployer/management/commands/aws/dev_tools.py
quintoandar_eb_deployer-3.1.dist-info/LICENSE
quintoandar_eb_deployer-3.1.dist-info/METADATA
quintoandar_eb_deployer-3.1.dist-info/WHEEL
quintoandar_eb_deployer-3.1.dist-info/entry_points.txt
quintoandar_eb_deployer-3.1.dist-info/top_level.txt
quintoandar_eb_deployer-3.1.dist-info/RECORD
