Metadata-Version: 2.1
Name: quintoandar-eb-deployer
Version: 3.1
Summary: Make your project publishes itself to AWS
Home-page: https://github.com/quintoandar/eb_deployer
Author: Diego Queiroz
Author-email: diego.queiroz@gmail.com
License: MIT
Platform: UNKNOWN
Classifier: Development Status :: 4 - Beta
Classifier: Environment :: Web Environment
Classifier: Framework :: Django
Classifier: Intended Audience :: Developers
Classifier: License :: OSI Approved :: MIT License
Classifier: Natural Language :: English
Classifier: Operating System :: POSIX :: Linux
Classifier: Programming Language :: Python
Classifier: Topic :: System :: Installation/Setup
Requires-Dist: Django
Requires-Dist: python-magic
